Workbook
Name solver_drv: 1
Name solver_eng: 1
Name solver_est: 1
Name solver_itr: 2147483647
Name solver_mip: 2147483647
Name solver_mni: 30
Name solver_msl: 2
Name solver_neg: 1
Name solver_nod: 2147483647
Name solver_num: 0
Name solver_nwt: 1
Name solver_rbv: 1
Name solver_rel0: 3
Name solver_rel1: 3
Name solver_rel2: 1
Name solver_rel3: 3
Name solver_rlx: 2
Name solver_rsd: 0
Name solver_scl: 1
Name solver_sho: 2
Name solver_ssz: 100
Name solver_tim: 2147483647
Name solver_tol: 0.01
Name solver_typ: 3
Name solver_val: 218.3
Name solver_ver: 3
Name solver_lhs3: DDM!$B$13:$E$13
Name solver_rhs1: DDM!$B$8:$E$8
Name solver_opt: DDM!$I$19
Name solver_adj: DDM!$I$16
Name solver_lhs1: DDM!$B$13:$E$13
Name solver_rhs3: DDM!$B$8:$E$8
Name solver_rhs0: DDM!$B$8:$E$8
Name solver_lhs2: DDM!$B$13:$E$13
Name solver_rhs2: DDM!$B$9:$E$9
Name solver_lhs0: DDM!$B$13:$E$13

Sheet DDM
B1: Dividend Discount Model (DDM)
B2: Broadcom Inc (AVGO)
B3: Year | C3: Quartely Dividend | D3: Annual Dividend | E3: Growth
B4: 2025 | C4: =(0.59+0.59+0.59+0.65)/4 -> 0.605 | D4: =C4*4 -> 2.42 | E4: =1+((D4-D5)/D5) -> 1.1152074
B5: 2024 | C5: =(0.525+0.525+0.53+0.59)/4 -> 0.5425 | D5: =C5*4 -> 2.17 | E5: =1+((D5-D6)/D6) -> 1.1391076
B6: 2023 | C6: =(0.46+0.46+0.46+0.525)/4 -> 0.47625 | D6: =C6*4 -> 1.905 | E6: =1+((D6-D7)/D7) -> 1.1272189
B7: 2022 | C7: =(0.41+0.41+0.41+0.46)/4 -> 0.4225 | D7: =C7*4 -> 1.69 | E7: =1+((D7-D8)/D8) -> 1.1342282
B8: 2021 | C8: =(0.36+0.36+0.36+0.41)/4 -> 0.3725 | D8: =C8*4 -> 1.49 | E8: =1+((D8-D9)/D9) -> 1.1161049
B9: 2020 | C9: =(0.325+0.325+0.325+0.36)/4 -> 0.33375 | D9: =C9*4 -> 1.335 | E9: =1+((D9-D10)/D10) -> 1.1919643
B10: 2019 | C10: =(0.265+0.265+0.265+0.325)/4 -> 0.28 | D10: =C10*4 -> 1.12 | E10: =1+((D10-D11)/D11) -> 0.98245614
B11: 2018 | C11: =(0.35+0.35+0.175+0.265)/4 -> 0.285 | D11: =C11*4 -> 1.14 | E11: =1+((D11-D12)/D12) -> 2.3700624
B12: 2017 | C12: =(0.102+0.102+0.102+0.175)/4 -> 0.12025 | D12: =C12*4 -> 0.481 | E12: =1+((D12-D13)/D13) -> 1.9087302
B13: 2016 | C13: =(0.049+0.05+0.051+0.102)/4 -> 0.063 | D13: =C13*4 -> 0.252 | E13: N/A | G13: Required Return (R) Solver
B15: Dividend Growth (g) | D15: =-1+(GEOMEAN(E4:E10)) -> 0.11352892 | G15: Dividend Growth (g) | I15: =D15 -> 0.11352892
B16: Required Return (r) | D16: =(D4*(1-D15)/D18)+D15 -> 0.11987585 | G16: Required Return (r) | I16: 0.069476276
B18: Current Price | D18: 338 | G18: Current Price | I18: 67.54
B19: DDM Price | D19: =D4/(D16-D15) -> 381.28712 | G19: DDM Price | I19: =D4/(I16-I15) -> -54.934269
B20: Overvalued or Undervalued | D20: =IF(D19>D18, "Undervalued", "Overvalued") -> Undervalued | G20: Overvalued or Undervalued | I20: =IF(I19>I18, "Undervalued", "Overvalued") -> Overvalued

Sheet DCF
B1: Discounted Cash Flow Analysis Model
B2: Broadcom Inc (AVGO)
B3: Year | C3: 2015 | D3: 2016 | E3: 2017 | F3: 2018 | G3: 2019 | H3: 2020 | I3: 2021 | J3: 2022 | K3: 2023 | L3: 2024
B4: Free Cash Flow | C4: 1835 | D4: 2693 | E4: 5923 | F4: 8484 | G4: 9353 | H4: 11598 | I4: 13321 | J4: 16312 | K4: 17633 | L4: 19414
B5: Growth | C5: N/A | D5: =(D4-C4)/C4 -> 0.46757493 | E5: =(E4-D4)/D4 -> 1.1994059 | F5: =(F4-E4)/E4 -> 0.43238224 | G5: =(G4-F4)/F4 -> 0.1024281 | H5: =(H4-G4)/G4 -> 0.24002994 | I5: =(I4-H4)/H4 -> 0.1485601 | J5: =(J4-I4)/I4 -> 0.22453269 | K5: =(K4-J4)/J4 -> 0.080983325 | L5: =(L4-K4)/K4 -> 0.1010038
B6: Average Growth Rate: | C6: =AVERAGE(D5:L5) -> 0.332989
C8: 1 | D8: 2 | E8: 3 | F8: 4 | G8: 5 | H8: 6 | I8: 7 | J8: 8 | K8: 9 | L8: 10
B9: Year | C9: 2026 | D9: 2027 | E9: 2028 | F9: 2029 | G9: 2030 | H9: 2031 | I9: 2032 | J9: 2033 | K9: 2034 | L9: Terminal Value
B10: Future Free Cash Flows | C10: =L4*(1+C6) -> 25878.648 | D10: =C10*(1+$C$6) -> 34495.954 | E10: =D10*(1+$C$6) -> 45982.727 | F10: =E10*(1+$C$6) -> 61294.469 | G10: =F10*(1+$C$6) -> 81704.853 | H10: =G10*(1+$C$6) -> 108911.67 | I10: =H10*(1+$C$6) -> 145178.06 | J10: =I10*(1+$C$6) -> 193520.75 | K10: =J10*(1+$C$6) -> 257961.04 | L10: =K10*(1+C12)/(C13-C12) -> 4807455.7
B11: PV | C11: =C10/(1+$C$13)^C8 -> 23961.712 | D11: =D10/(1+$C$13)^D8 -> 29574.72 | E11: =E10/(1+$C$13)^E8 -> 36502.571 | F11: =F10/(1+$C$13)^F8 -> 45053.264 | G11: =G10/(1+$C$13)^G8 -> 55606.95 | H11: =H10/(1+$C$13)^H8 -> 68632.826 | I11: =I10/(1+$C$13)^I8 -> 84710.002 | J11: =J10/(1+$C$13)^J8 -> 104553.24 | ... L11: =L10/(1+$C$13)^L8 -> 2226782.2
B12: Perpetual Growth Rate: | C12: 0.025
B13: Discount Rate: | C13: 0.08
B15: Total FCF | C15: =SUM(C11:L11) -> 2804422.2
B16: Cash + Equivalents | C16: 16178
B17: Total Debt | C17: 65136
B18: Equity Value | C18: =C15+C16-C17 -> 2755464.2
B19: Shares Outstanding | C19: 4740
B20: Margin of Safety | C20: 0
B21: DCF Share Price | C21: =(C18/C19)*(1-C20) -> 581.32156
B23: Current Price | C23: 339
B24: Difference | C24: =(C21-C23)/C23 -> 0.71481286

Sheet Multiples
B1: Multiples Valuation Model
B2: Broadcom Inc (AVGO)
B3: Ticker | C3: Company Name | D3: Stock Price | E3: EPS | F3: P/E Multiple
B4: NVDA | C4: Nvidia | D4: 182 | E4: 4.06 | F4: =D4/E4 -> 44.827586
B5: AMD | C5: Advanced Micro Devices | D5: 222 | E5: 2.03 | F5: =D5/E5 -> 109.35961
B6: QCOM | C6: Qualcomm | D6: 163 | E6: 5.05 | F6: =D6/E6 -> 32.277228
B7: TSMC | C7: Taiwan Semiconductor Manufacturing Co | D7: 325.49 | E7: 9.61 | F7: =D7/E7 -> 33.869927
B9: Average P/E | C9: =AVERAGE(F4:F7) -> 55.083587
B10: Median P/E | C10: =MEDIAN(F4:F7) -> 39.348757
B12: Ticker | C12: Stock Price | D12: Forward EPS
B13: KO | C13: =C9*D13 -> 375.67006 | D13: 6.82

Sheet Grahams Revised
B1: Benjamin Graham's Revised Valuation Model
B2: Broadcom Inc (AVGO)
B3: Ticker | C3: AVGO
B4: Forward EPS | C4: 6.82
B5: P/E Constant | C5: 7
B6: Est. EPS Growth Rate | C6: 40
B7: Growth Constant | C7: 1.5
B8: Average Yield of AAA Corp Bonds Constant | C8: 4.4
B9: Current Yield of AAA Corp Bonds | C9: 5.31
B11: Graham's Intrinsic Value | C11: =(C4*(C5+(C7*C6))*C8/C9) -> 378.63202

Sheet Peter Lynchs Adapted FV
B1: Peter Lynch's Adapted FV
B2: Broadcom Inc (AVGO)
B3: Ticker | C3: AVGO
B4: Forward EPS | C4: 6.82
B5: Forward P/E | C5: 35
B6: PEG | C6: 0.99
B7: Projected EPS Growth Rate | C7: 40
B8: 10y Avg EBITDA Growth Rate | C8: =(1+((7.23/5.23)/5.23)^1/10-1)*100 -> 2.6432298 | D8: N/A
B9: Current Price | C9: 338
B11: Fair Value | C11: =C6*C7*C4 -> 270.072

Sheet Final Valuation Analysis
B1: Final Valuation Analysis
B2: Broadcom Inc (AVGO)
B3: DDM | C3: =DDM!D19 -> 381.28712
B4: DCF | C4: =DCF!C21 -> 581.32156
B5: Multiples | C5: =Multiples!C13 -> 375.67006
B6: Graham's Revised | C6: ='Grahams Revised'!C11 -> 378.63202
B7: Peter Lynch's Adapted FV | C7: ='Peter Lynchs Adapted FV'!C11 -> 270.072
B9: Average Fair Value | C9: =AVERAGE(C3:C7) -> 397.39655
B11: Current Price | C11: 338.5
B12: Overvalued or Undervalued | C12: =IF(C9>C11, "Undervalued", "Overvalued") -> Undervalued
B13: Difference | C13: =(C11/C9)-1 -> -0.14820599
B14: MoS | C14: 0.1
B15: Limit Buy Price | C15: =(1-C14)*C9 -> 357.6569
